setup.py
disorg/__init__.py
disorg/__main__.py
disorg.egg-info/PKG-INFO
disorg.egg-info/SOURCES.txt
disorg.egg-info/dependency_links.txt
disorg.egg-info/entry_points.txt
disorg.egg-info/top_level.txt