Metadata-Version: 1.2
Name: disorg
Version: 0.0.1
Summary: Rapid note and task tracking application.
Home-page: https://gitlab.com/zaccrites/disorg
Author: Zachary Crites
Author-email: UNKNOWN
License: MIT
Platform: UNKNOWN
Requires-Python: >=3.6
